krypton/lib/__init__.py
krypton/lib/model/__init__.py
krypton/lib/model/base.py
krypton/lib/model/exchange/__init__.py
krypton/lib/model/exchange/info.py
krypton/lib/model/exchange/stream.py
krypton/lib/model/shared/__init__.py
krypton/lib/model/shared/resource.py
krypton/lib/py.typed
krypton_lib-0.1.0.dev5.dist-info/LICENSE
krypton_lib-0.1.0.dev5.dist-info/METADATA
krypton_lib-0.1.0.dev5.dist-info/WHEEL
krypton_lib-0.1.0.dev5.dist-info/RECORD
